{
    "experiment_config": {
        "mode": "simple",
        "num_categories": 5,
        "p": 0.2,
        "num_nodes": 20,
        "motif_dim": 0,
        "num_train_samples": 10000,
        "num_test_samples": 1500,
        "batch_size": 16,
        "in_dim": 5,
        "hidden_dims": [
            5,
            2
        ],
        "lr": 0.01,
        "use_weighting": true,
        "importance": [
            15.0,
            10.0
        ],
        "phase1_epochs": 30,
        "phase2_epochs": 50,
        "device": "cpu",
        "model_type": "GCN",
        "loss": "BCE",
        "pooling": "mean",
        "gm_p": 1.0,
        "log_dir": "runs/T/BCE/2/GCN/small_compression/mean/5/high",
        "file_path": "T/BCE/2/GCN/small_compression/mean/5/high",
        "add_graph": false,
        "track_embeddings": false,
        "track_singular_values": true,
        "get_elements": false,
        "save": true
    },
    "sparcity": 0.9710727785415598,
    "empty_graph_stats": [
        {
            "mean": [
                -0.1387985795736313,
                0.07284218817949295
            ],
            "std": [
                0.5232207775115967,
                0.5451316237449646
            ]
        },
        {
            "mean": [
                0.5446184277534485,
                -0.2601674497127533
            ],
            "std": [
                0.6957469582557678,
                0.514665424823761
            ]
        },
        {
            "mean": [
                0.42651405930519104,
                0.15862049162387848
            ],
            "std": [
                0.711847186088562,
                1.4530454874038696
            ]
        },
        {
            "mean": [
                1.0251562595367432,
                -0.16070984303951263
            ],
            "std": [
                0.9940294623374939,
                1.2707315683364868
            ]
        },
        {
            "mean": [
                0.38307562470436096,
                0.7392817735671997
            ],
            "std": [
                1.3206830024719238,
                1.610148549079895
            ]
        },
        {
            "mean": [
                -0.4312717616558075,
                -0.06612634658813477
            ],
            "std": [
                0.7830851674079895,
                1.459960699081421
            ]
        },
        {
            "mean": [
                -0.13346222043037415,
                0.00019575736951082945
            ],
            "std": [
                0.4435793161392212,
                0.32618993520736694
            ]
        },
        {
            "mean": [
                -0.33118849992752075,
                1.2549160718917847
            ],
            "std": [
                0.4076589345932007,
                1.4343352317810059
            ]
        },
        {
            "mean": [
                -0.11411957442760468,
                -0.10265613347291946
            ],
            "std": [
                0.2490164190530777,
                0.24112007021903992
            ]
        },
        {
            "mean": [
                -0.5513812899589539,
                0.20900455117225647
            ],
            "std": [
                0.5953450798988342,
                0.41991832852363586
            ]
        },
        {
            "mean": [
                -0.074078768491745,
                -0.5951704382896423
            ],
            "std": [
                0.6005845069885254,
                0.5615590810775757
            ]
        },
        {
            "mean": [
                -0.29516881704330444,
                -0.3807217478752136
            ],
            "std": [
                0.2652400732040405,
                0.5626765489578247
            ]
        },
        {
            "mean": [
                0.02751832827925682,
                -0.05063706636428833
            ],
            "std": [
                0.24164441227912903,
                0.2541705071926117
            ]
        },
        {
            "mean": [
                -0.4908331632614136,
                -0.15654951333999634
            ],
            "std": [
                0.9769766330718994,
                1.1926125288009644
            ]
        },
        {
            "mean": [
                0.11085478961467743,
                0.19348305463790894
            ],
            "std": [
                0.3458222448825836,
                0.44666677713394165
            ]
        }
    ],
    "summary format:": "Key: (Num of active features, Num of accurate feature, Geometry, Collapsed). Loss, s.d. Loss, Count",
    "collapsed percentage": 60.0,
    "summary": {
        "(4, 4, 4, 0)": [
            0.07118764846523602,
            0.012491982740079486,
            7
        ],
        "(3, 2, 'Failed', 0)": [
            0.15178643294175465,
            0.0,
            1
        ],
        "(3, 1, 'Failed', 0)": [
            0.15878881653149923,
            0.0,
            1
        ],
        "(3, 0, 3, 0)": [
            0.17942985932032268,
            0.0,
            1
        ],
        "(2, 1, 2, 0)": [
            0.1450659520758523,
            0.003076148311765421,
            3
        ],
        "(3, 3, 'Failed', 0)": [
            0.09062057882547378,
            0.0,
            1
        ],
        "(4, 3, 4, 0)": [
            0.12429555914799373,
            0.0,
            1
        ]
    },
    "results": [
        {
            "Num of features": 5,
            "Num of active features": 4,
            "Num of accurate feature": 4,
            "Geometry": 4,
            "Collapsed": 0,
            "Loss": 0.06533145506183306,
            "Rank": 2,
            "Singular values": [
                6.771090030670166,
                5.677285671234131
            ]
        },
        {
            "Num of features": 5,
            "Num of active features": 4,
            "Num of accurate feature": 4,
            "Geometry": 4,
            "Collapsed": 0,
            "Loss": 0.10004248764117558,
            "Rank": 2,
            "Singular values": [
                5.117097854614258,
                4.696579933166504
            ]
        },
        {
            "Num of features": 5,
            "Num of active features": 3,
            "Num of accurate feature": 2,
            "Geometry": "Failed",
            "Collapsed": 0,
            "Loss": 0.15178643294175465,
            "Rank": 2,
            "Singular values": [
                4.165751934051514,
                3.296847343444824
            ]
        },
        {
            "Num of features": 5,
            "Num of active features": 3,
            "Num of accurate feature": 1,
            "Geometry": "Failed",
            "Collapsed": 0,
            "Loss": 0.15878881653149923,
            "Rank": 2,
            "Singular values": [
                3.927643060684204,
                3.6160953044891357
            ]
        },
        {
            "Num of features": 5,
            "Num of active features": 3,
            "Num of accurate feature": 0,
            "Geometry": 3,
            "Collapsed": 0,
            "Loss": 0.17942985932032268,
            "Rank": 2,
            "Singular values": [
                4.093369483947754,
                4.025462627410889
            ]
        },
        {
            "Num of features": 5,
            "Num of active features": 2,
            "Num of accurate feature": 1,
            "Geometry": 2,
            "Collapsed": 0,
            "Loss": 0.1451533346970876,
            "Rank": 2,
            "Singular values": [
                6.055124282836914,
                3.707812786102295
            ]
        },
        {
            "Num of features": 5,
            "Num of active features": 4,
            "Num of accurate feature": 4,
            "Geometry": 4,
            "Collapsed": 0,
            "Loss": 0.07032803189754486,
            "Rank": 2,
            "Singular values": [
                4.289955139160156,
                3.0225753784179688
            ]
        },
        {
            "Num of features": 5,
            "Num of active features": 2,
            "Num of accurate feature": 1,
            "Geometry": 2,
            "Collapsed": 0,
            "Loss": 0.14125552399953206,
            "Rank": 2,
            "Singular values": [
                4.595035076141357,
                2.820858955383301
            ]
        },
        {
            "Num of features": 5,
            "Num of active features": 4,
            "Num of accurate feature": 4,
            "Geometry": 4,
            "Collapsed": 0,
            "Loss": 0.07039479188124338,
            "Rank": 2,
            "Singular values": [
                3.3751914501190186,
                2.882883310317993
            ]
        },
        {
            "Num of features": 5,
            "Num of active features": 3,
            "Num of accurate feature": 3,
            "Geometry": "Failed",
            "Collapsed": 0,
            "Loss": 0.09062057882547378,
            "Rank": 2,
            "Singular values": [
                4.43217134475708,
                3.730090618133545
            ]
        },
        {
            "Num of features": 5,
            "Num of active features": 4,
            "Num of accurate feature": 3,
            "Geometry": 4,
            "Collapsed": 0,
            "Loss": 0.12429555914799373,
            "Rank": 2,
            "Singular values": [
                4.331155776977539,
                3.756451368331909
            ]
        },
        {
            "Num of features": 5,
            "Num of active features": 4,
            "Num of accurate feature": 4,
            "Geometry": 4,
            "Collapsed": 0,
            "Loss": 0.06951385738452276,
            "Rank": 2,
            "Singular values": [
                5.8116068840026855,
                2.5866427421569824
            ]
        },
        {
            "Num of features": 5,
            "Num of active features": 4,
            "Num of accurate feature": 4,
            "Geometry": 4,
            "Collapsed": 0,
            "Loss": 0.057624512036641436,
            "Rank": 2,
            "Singular values": [
                3.37204909324646,
                2.6943795680999756
            ]
        },
        {
            "Num of features": 5,
            "Num of active features": 2,
            "Num of accurate feature": 1,
            "Geometry": 2,
            "Collapsed": 0,
            "Loss": 0.1487889975309372,
            "Rank": 2,
            "Singular values": [
                3.8360238075256348,
                3.2204322814941406
            ]
        },
        {
            "Num of features": 5,
            "Num of active features": 4,
            "Num of accurate feature": 4,
            "Geometry": 4,
            "Collapsed": 0,
            "Loss": 0.0650784033536911,
            "Rank": 2,
            "Singular values": [
                3.5492746829986572,
                2.908535957336426
            ]
        }
    ],
    "average embeddings summary": {
        "(4, 4, 4, 0)": {
            "(1, 0, 0, 0, 0)": [
                4.301988124847412,
                0.7356298565864563
            ],
            "(0, 0, 0, 0, 1)": [
                -0.02285270020365715,
                -5.1199750900268555
            ],
            "(0, 0, 1, 0, 0)": [
                -0.1810244768857956,
                -0.053533121943473816
            ],
            "(0, 0, 0, 1, 0)": [
                -4.009449481964111,
                -0.5807785391807556
            ],
            "(0, 1, 0, 0, 0)": [
                -0.10755795985460281,
                4.044270038604736
            ]
        },
        "(3, 2, 'Failed', 0)": {
            "(0, 0, 0, 1, 0)": [
                -3.625542402267456,
                -0.3383544683456421
            ],
            "(0, 0, 1, 0, 0)": [
                0.19000305235385895,
                2.633756399154663
            ],
            "(0, 1, 0, 0, 0)": [
                1.9158703088760376,
                0.23758269846439362
            ],
            "(0, 0, 0, 0, 1)": [
                0.4684145748615265,
                -1.9868543148040771
            ],
            "(1, 0, 0, 0, 0)": [
                0.22648313641548157,
                -0.21348518133163452
            ]
        },
        "(3, 1, 'Failed', 0)": {
            "(0, 0, 0, 0, 1)": [
                2.252213478088379,
                -2.1042733192443848
            ],
            "(0, 0, 0, 1, 0)": [
                -1.6773550510406494,
                -2.078603506088257
            ],
            "(0, 0, 1, 0, 0)": [
                -0.6552479863166809,
                2.2813663482666016
            ],
            "(0, 1, 0, 0, 0)": [
                1.9841734170913696,
                1.0283234119415283
            ],
            "(1, 0, 0, 0, 0)": [
                1.1027607917785645,
                -0.1533711701631546
            ]
        },
        "(3, 0, 3, 0)": {
            "(1, 0, 0, 0, 0)": [
                1.5280269384384155,
                -1.2642754316329956
            ],
            "(0, 0, 0, 1, 0)": [
                -2.2988498210906982,
                -1.7555464506149292
            ],
            "(0, 0, 0, 0, 1)": [
                0.36751508712768555,
                1.3250420093536377
            ],
            "(0, 0, 1, 0, 0)": [
                -2.247274398803711,
                2.6966402530670166
            ],
            "(0, 1, 0, 0, 0)": [
                1.9026343822479248,
                1.6814206838607788
            ]
        },
        "(2, 1, 2, 0)": {
            "(0, 1, 0, 0, 0)": [
                -0.04572277516126633,
                2.439730405807495
            ],
            "(0, 0, 0, 1, 0)": [
                -0.3377200663089752,
                -0.586004912853241
            ],
            "(0, 0, 0, 0, 1)": [
                -0.4209566116333008,
                -2.6253795623779297
            ],
            "(0, 0, 1, 0, 0)": [
                -2.13562273979187,
                -0.41481098532676697
            ],
            "(1, 0, 0, 0, 0)": [
                5.615781307220459,
                -0.8128949403762817
            ]
        },
        "(3, 3, 'Failed', 0)": {
            "(0, 0, 1, 0, 0)": [
                -0.48593831062316895,
                -0.20705865323543549
            ],
            "(1, 0, 0, 0, 0)": [
                3.412635564804077,
                -0.10400181263685226
            ],
            "(0, 0, 0, 1, 0)": [
                -1.8403878211975098,
                0.29462945461273193
            ],
            "(0, 1, 0, 0, 0)": [
                0.5885021686553955,
                3.350003957748413
            ],
            "(0, 0, 0, 0, 1)": [
                -0.6398831009864807,
                -2.4838809967041016
            ]
        },
        "(4, 3, 4, 0)": {
            "(0, 0, 0, 0, 1)": [
                1.4552178382873535,
                -3.2555439472198486
            ],
            "(1, 0, 0, 0, 0)": [
                3.85701584815979,
                1.1428056955337524
            ],
            "(0, 0, 0, 1, 0)": [
                -1.1579593420028687,
                -1.4370179176330566
            ],
            "(0, 0, 1, 0, 0)": [
                -0.23887544870376587,
                0.2780936360359192
            ],
            "(0, 1, 0, 0, 0)": [
                0.023968568071722984,
                -0.6558750867843628
            ]
        }
    },
    "model summary": {
        "(4, 4, 4, 0)": {
            "convs.0.bias": [
                -5.2541351318359375,
                -4.120889663696289,
                -4.9679436683654785,
                -2.4099133014678955,
                -5.170317649841309
            ],
            "convs.0.lin.weight": [
                [
                    0.20198115706443787,
                    -0.7148021459579468,
                    -0.5357163548469543,
                    10.558094024658203,
                    -0.14930014312267303
                ],
                [
                    0.4267439842224121,
                    -0.5949494242668152,
                    -1.3810052871704102,
                    0.5824421048164368,
                    8.961585998535156
                ],
                [
                    9.865367889404297,
                    0.5053243041038513,
                    0.6996317505836487,
                    0.37061500549316406,
                    1.2741047143936157
                ],
                [
                    2.0519564151763916,
                    0.06977999955415726,
                    1.9718244075775146,
                    0.01850750483572483,
                    5.090944290161133
                ],
                [
                    1.3909666538238525,
                    10.295623779296875,
                    -0.17182032763957977,
                    0.21545922756195068,
                    2.461956262588501
                ]
            ],
            "convs.1.bias": [
                -0.14246147871017456,
                0.09546635299921036
            ],
            "convs.1.lin.weight": [
                [
                    -19.15066909790039,
                    1.3892890214920044,
                    24.741010665893555,
                    -2.296527862548828,
                    0.2007715255022049
                ],
                [
                    -3.5209414958953857,
                    -21.034427642822266,
                    3.9280202388763428,
                    -4.878626346588135,
                    21.173376083374023
                ]
            ],
            "lin_out.weight": [
                [
                    2.6701836585998535,
                    -0.23625707626342773
                ],
                [
                    -0.43631136417388916,
                    2.4872496128082275
                ],
                [
                    -0.06449960172176361,
                    0.035658277571201324
                ],
                [
                    -2.9591193199157715,
                    0.08822544664144516
                ],
                [
                    0.44363632798194885,
                    -2.918703556060791
                ]
            ],
            "lin_out.bias": [
                -6.145565032958984,
                -6.65537166595459,
                -1.8818737268447876,
                -7.08797550201416,
                -6.1628031730651855
            ]
        },
        "(3, 2, 'Failed', 0)": {
            "convs.0.bias": [
                0.26642942428588867,
                0.30368927121162415,
                0.2537898123264313,
                -4.530213832855225,
                -0.17259487509727478
            ],
            "convs.0.lin.weight": [
                [
                    -0.07573778927326202,
                    6.964537143707275,
                    -0.2857195734977722,
                    1.6703633069992065,
                    3.815807342529297
                ],
                [
                    0.524311363697052,
                    3.7630295753479004,
                    7.186326026916504,
                    1.877732276916504,
                    -0.36722129583358765
                ],
                [
                    0.3947530686855316,
                    -0.2461971938610077,
                    0.13072893023490906,
                    1.6574207544326782,
                    6.645930767059326
                ],
                [
                    -0.9140368103981018,
                    1.1829290390014648,
                    1.609800934791565,
                    9.956722259521484,
                    0.09402165561914444
                ],
                [
                    -0.6298980116844177,
                    -0.7069477438926697,
                    0.14832130074501038,
                    0.10964173078536987,
                    -0.31448590755462646
                ]
            ],
            "convs.1.bias": [
                -0.13382543623447418,
                -0.032608773559331894
            ],
            "convs.1.lin.weight": [
                [
                    2.1165881156921387,
                    -0.17575599253177643,
                    -1.2525044679641724,
                    -15.717423439025879,
                    0.5967607498168945
                ],
                [
                    -1.7569645643234253,
                    3.480193853378296,
                    -2.3886024951934814,
                    -1.8336786031723022,
                    -0.04294891282916069
                ]
            ],
            "lin_out.weight": [
                [
                    0.17325294017791748,
                    0.006970930378884077
                ],
                [
                    2.540090560913086,
                    0.13454008102416992
                ],
                [
                    -0.051604628562927246,
                    1.2424712181091309
                ],
                [
                    -3.6809213161468506,
                    -0.24859818816184998
                ],
                [
                    0.36262959241867065,
                    -1.1522208452224731
                ]
            ],
            "lin_out.bias": [
                -1.8579792976379395,
                -4.476223945617676,
                -3.0480570793151855,
                -5.831878662109375,
                -2.798163652420044
            ]
        },
        "(3, 1, 'Failed', 0)": {
            "convs.0.bias": [
                -2.412827253341675,
                2.2067956924438477,
                1.7770940065383911,
                1.2531129121780396,
                1.298067331314087
            ],
            "convs.0.lin.weight": [
                [
                    0.3844659924507141,
                    0.4879641532897949,
                    -0.2343151569366455,
                    8.83376693725586,
                    0.4114522635936737
                ],
                [
                    1.832045555114746,
                    -1.309269666671753,
                    -0.8959053158760071,
                    -9.671662330627441,
                    5.006128787994385
                ],
                [
                    1.4256038665771484,
                    2.3495829105377197,
                    0.7556493282318115,
                    -2.6165804862976074,
                    1.4079601764678955
                ],
                [
                    1.5423592329025269,
                    -0.8398963809013367,
                    5.876420974731445,
                    -7.937820911407471,
                    -1.4851644039154053
                ],
                [
                    2.1398847103118896,
                    0.7886980772018433,
                    -0.05411631613969803,
                    -1.898977518081665,
                    5.3108625411987305
                ]
            ],
            "convs.1.bias": [
                1.3492127656936646,
                2.4402036666870117
            ],
            "convs.1.lin.weight": [
                [
                    -7.2602691650390625,
                    -1.8625906705856323,
                    2.1158947944641113,
                    -3.1128990650177,
                    2.7148680686950684
                ],
                [
                    -6.363962173461914,
                    -5.0624871253967285,
                    2.2846686840057373,
                    2.5701935291290283,
                    0.7135540246963501
                ]
            ],
            "lin_out.weight": [
                [
                    0.06178659573197365,
                    0.06736087054014206
                ],
                [
                    1.814030408859253,
                    1.2369351387023926
                ],
                [
                    -0.6979795694351196,
                    1.0539525747299194
                ],
                [
                    -3.7120208740234375,
                    -2.205172538757324
                ],
                [
                    0.7602331638336182,
                    -0.9768239259719849
                ]
            ],
            "lin_out.bias": [
                -1.8295378684997559,
                -4.423647880554199,
                -2.5332391262054443,
                -5.997476100921631,
                -3.3161652088165283
            ]
        },
        "(3, 0, 3, 0)": {
            "convs.0.bias": [
                0.7151659727096558,
                0.0,
                0.36510294675827026,
                0.245952308177948,
                -2.5344722270965576
            ],
            "convs.0.lin.weight": [
                [
                    -0.7246513366699219,
                    -0.9408212304115295,
                    4.705393314361572,
                    1.8320428133010864,
                    1.7703543901443481
                ],
                [
                    -0.3766167461872101,
                    -0.7410457134246826,
                    -0.29325592517852783,
                    -0.07232092320919037,
                    -0.7056896090507507
                ],
                [
                    6.817259788513184,
                    2.028258800506592,
                    -0.49427270889282227,
                    5.014865875244141,
                    1.1648892164230347
                ],
                [
                    1.2780027389526367,
                    6.791716575622559,
                    6.080020904541016,
                    -0.20323261618614197,
                    1.5831949710845947
                ],
                [
                    0.1616060882806778,
                    0.1899959146976471,
                    5.960574626922607,
                    7.18339729309082,
                    -0.7826269865036011
                ]
            ],
            "convs.1.bias": [
                0.220781609416008,
                0.5110441446304321
            ],
            "convs.1.lin.weight": [
                [
                    -2.450521945953369,
                    -0.5232343077659607,
                    2.0449678897857666,
                    1.1886235475540161,
                    -12.51896858215332
                ],
                [
                    0.6899265646934509,
                    -0.33971360325813293,
                    -3.38075590133667,
                    3.261713743209839,
                    -2.550267219543457
                ]
            ],
            "lin_out.weight": [
                [
                    0.7188376784324646,
                    -0.6476221680641174
                ],
                [
                    1.2211281061172485,
                    0.8675037622451782
                ],
                [
                    -0.8512865304946899,
                    0.8255641460418701
                ],
                [
                    -1.0428615808486938,
                    -1.1165621280670166
                ],
                [
                    0.1446639597415924,
                    0.0644061490893364
                ]
            ],
            "lin_out.bias": [
                -2.915403366088867,
                -3.220383644104004,
                -3.6915957927703857,
                -3.6082639694213867,
                -1.8960118293762207
            ]
        },
        "(2, 1, 2, 0)": {
            "convs.0.bias": [
                -4.972184181213379,
                -0.06005501747131348,
                0.10828400403261185,
                0.23942597210407257,
                0.09826990216970444
            ],
            "convs.0.lin.weight": [
                [
                    10.04838752746582,
                    0.39450329542160034,
                    0.7646238207817078,
                    -0.12801580131053925,
                    -1.965697169303894
                ],
                [
                    -0.7558086514472961,
                    -0.16470520198345184,
                    -0.03778035566210747,
                    -0.09313628822565079,
                    -0.3229677081108093
                ],
                [
                    0.7463080286979675,
                    8.333879470825195,
                    4.276490211486816,
                    0.3401287794113159,
                    -0.11389423161745071
                ],
                [
                    0.09814402461051941,
                    0.33063071966171265,
                    -0.1853906214237213,
                    2.0128135681152344,
                    7.132999420166016
                ],
                [
                    0.9495067596435547,
                    -0.04871467128396034,
                    6.292672157287598,
                    0.8614442348480225,
                    4.1065192222595215
                ]
            ],
            "convs.1.bias": [
                -0.009331599809229374,
                0.3158119022846222
            ],
            "convs.1.lin.weight": [
                [
                    24.990558624267578,
                    -0.0848955437541008,
                    0.23364706337451935,
                    1.5925427675247192,
                    -2.82963490486145
                ],
                [
                    -1.914484977722168,
                    -0.6160179376602173,
                    3.2540597915649414,
                    -1.9254672527313232,
                    -2.3247194290161133
                ]
            ],
            "lin_out.weight": [
                [
                    3.3613665103912354,
                    -0.3285805583000183
                ],
                [
                    -0.08625366538763046,
                    1.2516802549362183
                ],
                [
                    -1.963983178138733,
                    0.1915823519229889
                ],
                [
                    -0.1929633617401123,
                    -0.10540934652090073
                ],
                [
                    -0.14798516035079956,
                    -0.9984112977981567
                ]
            ],
            "lin_out.bias": [
                -7.602500915527344,
                -3.385496139526367,
                -3.825035810470581,
                -1.7290012836456299,
                -2.581794261932373
            ]
        },
        "(3, 3, 'Failed', 0)": {
            "convs.0.bias": [
                -0.7605484127998352,
                -3.514097213745117,
                -5.000578880310059,
                -4.395598411560059,
                -0.6083029508590698
            ],
            "convs.0.lin.weight": [
                [
                    0.3248988091945648,
                    2.9761881828308105,
                    3.692586660385132,
                    0.9566836357116699,
                    1.6084508895874023
                ],
                [
                    0.2915910482406616,
                    -0.14939376711845398,
                    -0.711165726184845,
                    -0.07103573530912399,
                    8.505131721496582
                ],
                [
                    9.931784629821777,
                    0.8011800050735474,
                    -0.2867114245891571,
                    1.2813265323638916,
                    1.2629976272583008
                ],
                [
                    -0.17207330465316772,
                    8.447952270507812,
                    0.6582468152046204,
                    -0.15665464103221893,
                    0.4238668382167816
                ],
                [
                    0.5353615880012512,
                    0.20914840698242188,
                    0.6472058892250061,
                    6.730668067932129,
                    -0.02278505638241768
                ]
            ],
            "convs.1.bias": [
                -0.19900019466876984,
                0.40828537940979004
            ],
            "convs.1.lin.weight": [
                [
                    0.2507868707180023,
                    0.17337831854820251,
                    20.690265655517578,
                    7.16020393371582,
                    -2.4373836517333984
                ],
                [
                    -1.813419222831726,
                    -11.0390043258667,
                    -1.4252301454544067,
                    22.121952056884766,
                    0.18971720337867737
                ]
            ],
            "lin_out.weight": [
                [
                    3.481158971786499,
                    -0.8594735264778137
                ],
                [
                    0.30905014276504517,
                    4.102558612823486
                ],
                [
                    -0.09046965092420578,
                    -0.20078690350055695
                ],
                [
                    -2.549701690673828,
                    0.37905606627464294
                ],
                [
                    -0.49773213267326355,
                    -4.00260591506958
                ]
            ],
            "lin_out.bias": [
                -6.797709941864014,
                -7.141967296600342,
                -1.912382960319519,
                -4.142054080963135,
                -5.093087673187256
            ]
        },
        "(4, 3, 4, 0)": {
            "convs.0.bias": [
                2.0556743144989014,
                -4.715326309204102,
                -4.239563465118408,
                -0.16368097066879272,
                2.0061872005462646
            ],
            "convs.0.lin.weight": [
                [
                    -0.2032739818096161,
                    0.4187040627002716,
                    -2.2928998470306396,
                    -2.300178289413452,
                    -0.028070900589227676
                ],
                [
                    9.698480606079102,
                    -0.3172660768032074,
                    1.0398476123809814,
                    1.1408241987228394,
                    0.2870970070362091
                ],
                [
                    -0.6856110692024231,
                    -0.5296843647956848,
                    -0.1267714500427246,
                    -0.980278730392456,
                    8.694658279418945
                ],
                [
                    -0.12291012704372406,
                    -0.20334936678409576,
                    0.14915266633033752,
                    -0.7131401896476746,
                    -0.7659923434257507
                ],
                [
                    -0.06678403913974762,
                    0.22793617844581604,
                    -2.798478126525879,
                    2.12992000579834,
                    -0.37134072184562683
                ]
            ],
            "convs.1.bias": [
                -3.196394443511963,
                5.454591751098633
            ],
            "convs.1.lin.weight": [
                [
                    3.534518241882324,
                    18.81965446472168,
                    8.900091171264648,
                    0.08542641252279282,
                    -1.8357068300247192
                ],
                [
                    0.441226989030838,
                    8.551965713500977,
                    -14.865994453430176,
                    -0.07607226073741913,
                    -3.4891905784606934
                ]
            ],
            "lin_out.weight": [
                [
                    3.07338285446167,
                    1.8540160655975342
                ],
                [
                    -0.16421657800674438,
                    0.06341952830553055
                ],
                [
                    -1.983097791671753,
                    3.5497748851776123
                ],
                [
                    -2.689846992492676,
                    -1.1820825338363647
                ],
                [
                    2.112114191055298,
                    -4.957879543304443
                ]
            ],
            "lin_out.bias": [
                -7.634045124053955,
                -1.6023979187011719,
                -1.420669674873352,
                -3.7761902809143066,
                -10.531522750854492
            ]
        }
    }
}