{
    "experiment_config": {
        "mode": "tox21",
        "root": "data/Tox21",
        "batch_size": 32,
        "train_split": 0.8,
        "mask_missing": true,
        "use_weighting": false,
        "importance": [
            100.0,
            100.0
        ],
        "hidden_dims": [
            12,
            12
        ],
        "num_categories": 12,
        "in_dim": 9,
        "lr": 0.001,
        "model_type": "GCN",
        "loss": "BCE",
        "pooling": "mean",
        "gm_p": 1.0,
        "device": "cpu",
        "phase1_epochs": 0,
        "phase2_epochs": 50,
        "log_dir": "runs/tox21/GCN/mean/[12, 12]",
        "file_path": "tox21/GCN/mean/[12, 12]",
        "save": true,
        "num_nodes": 20,
        "p": 0.8
    },
    "sparcity": 0.8694764120978721,
    "empty graph stats": 0.4005700647830963,
    "singular value ratio": [
        0.0,
        0.0
    ],
    "summary format:": "Key: (Num of active features, Num of accurate feature, Geometry, Collapsed). Loss, s.d. Loss, Count",
    "collapsed percentage": 0.0,
    "summary": {
        "(5, 0, 'Failed', 2)": [
            0.6226522310987695,
            0.0,
            1
        ]
    },
    "results": [
        {
            "Num of features": 12,
            "Num of active features": 5,
            "Num of accurate feature": 0,
            "Geometry": "Failed",
            "Collapsed": 2,
            "Loss": 0.6226522310987695,
            "Rank": 9,
            "Singular values": [
                10.248945236206055,
                1.2974399328231812,
                0.6408828496932983,
                0.6177688241004944,
                0.19558869302272797,
                0.06029660627245903,
                0.03658432140946388,
                0.013011257164180279,
                0.00915196631103754
            ]
        }
    ],
    "average embeddings summary": {
        "(5, 0, 'Failed', 2)": {
            "(0, 0, 0, 1, 0, 0, 0, 0, 0, 0, 0, 0)": [
                1.200647234916687,
                -0.01229771226644516,
                0.9121212959289551,
                1.224586844444275,
                -0.7461540699005127,
                -0.12120410054922104,
                -1.8047051429748535,
                -0.1863386034965515,
                0.3787494897842407,
                0.11764535307884216,
                -0.3602661192417145,
                0.6538062691688538
            ],
            "(0, 0, 0, 0, 0, 0, 0, 1, 0, 0, 0, 0)": [
                1.837177038192749,
                -0.4696432948112488,
                1.0180153846740723,
                1.3518909215927124,
                -0.8633411526679993,
                0.056496407836675644,
                -2.337116241455078,
                0.2325243204832077,
                0.4784558117389679,
                0.003723873756825924,
                -0.3879700005054474,
                0.5805688500404358
            ],
            "(1, 0, 0, 0, 0, 0, 0, 0, 0, 0, 0, 0)": [
                1.6452404260635376,
                -0.593816339969635,
                1.0124359130859375,
                1.3813755512237549,
                -1.2954782247543335,
                0.06678663939237595,
                -2.4414753913879395,
                -0.09934444725513458,
                0.6085535287857056,
                -0.07314039766788483,
                -0.3912777304649353,
                0.35512858629226685
            ],
            "(0, 0, 1, 0, 0, 0, 0, 0, 0, 0, 0, 0)": [
                1.22830331325531,
                0.03252536430954933,
                0.8982237577438354,
                1.21530020236969,
                -0.6773177981376648,
                -0.11395623534917831,
                -1.7431105375289917,
                -0.1249348521232605,
                0.36562380194664,
                0.18276889622211456,
                -0.37602898478507996,
                0.7085391283035278
            ],
            "(0, 0, 0, 0, 0, 0, 1, 0, 0, 0, 0, 0)": [
                1.205291509628296,
                -0.022669166326522827,
                0.8952917456626892,
                1.0065510272979736,
                -0.8636345863342285,
                0.030845828354358673,
                -1.914907455444336,
                -0.3226383924484253,
                0.4971272945404053,
                0.2744590938091278,
                -0.3852195739746094,
                0.6878762245178223
            ],
            "(0, 0, 0, 0, 1, 0, 0, 0, 0, 0, 0, 0)": [
                1.761706829071045,
                -0.6321597099304199,
                1.0437731742858887,
                1.3657594919204712,
                -1.218040943145752,
                0.11530206352472305,
                -2.5176360607147217,
                0.033995404839515686,
                0.5528101921081543,
                -0.07972367852926254,
                -0.399138480424881,
                0.5013651251792908
            ],
            "(0, 0, 0, 0, 0, 0, 0, 0, 0, 0, 1, 0)": [
                1.320642113685608,
                -0.3651294708251953,
                1.0263365507125854,
                1.3791217803955078,
                -1.2137010097503662,
                -0.06136326491832733,
                -2.2156624794006348,
                -0.2427120804786682,
                0.38490065932273865,
                -0.05275697633624077,
                -0.35659968852996826,
                0.5088648200035095
            ],
            "(0, 1, 0, 0, 0, 0, 0, 0, 0, 0, 0, 0)": [
                1.1015195846557617,
                -0.03527636080980301,
                0.862783670425415,
                0.8782438635826111,
                -0.9593203067779541,
                0.12359181046485901,
                -1.9305806159973145,
                -0.3734859526157379,
                0.45272985100746155,
                0.2996039390563965,
                -0.3857598900794983,
                0.8788449764251709
            ],
            "(0, 0, 0, 0, 0, 0, 0, 0, 0, 1, 0, 0)": [
                2.1438679695129395,
                -0.8809235692024231,
                1.0489634275436401,
                1.2676432132720947,
                -1.2667138576507568,
                0.34281012415885925,
                -2.8531289100646973,
                0.2583661377429962,
                0.6460430026054382,
                -0.07188314944505692,
                -0.4409072697162628,
                0.6338146328926086
            ]
        }
    },
    "model summary": {
        "(5, 0, 'Failed', 2)": {
            "convs.0.bias": [
                -0.006028009112924337,
                -0.06474166363477707,
                -0.02230837382376194,
                0.004146135877817869,
                0.07992257177829742,
                -0.028160151094198227,
                -0.04048902168869972,
                0.0,
                -0.14933273196220398,
                -0.011572526767849922,
                -0.01635625772178173,
                -0.03535114601254463
            ],
            "convs.0.lin.weight": [
                [
                    0.011042260564863682,
                    -0.6180415749549866,
                    0.4356839060783386,
                    0.33194711804389954,
                    0.024276895448565483,
                    -0.13138799369335175,
                    -0.5747032165527344,
                    0.47273483872413635,
                    0.3217041492462158
                ],
                [
                    0.5124194025993347,
                    -0.7826641201972961,
                    0.26136818528175354,
                    0.19596093893051147,
                    -0.4705294370651245,
                    0.9365463852882385,
                    -0.34448739886283875,
                    0.582042396068573,
                    -0.1768159121274948
                ],
                [
                    -0.024443233385682106,
                    0.8650929927825928,
                    0.029975220561027527,
                    0.3222871720790863,
                    -0.026733458042144775,
                    -0.41965603828430176,
                    -0.006120873615145683,
                    -0.4309011697769165,
                    0.16637025773525238
                ],
                [
                    0.4451717138290405,
                    -1.0859426259994507,
                    0.4608401954174042,
                    0.31322941184043884,
                    0.1436690390110016,
                    0.47590172290802,
                    -0.2426621913909912,
                    -0.3900053799152374,
                    0.21643845736980438
                ],
                [
                    0.21456946432590485,
                    -1.4418238401412964,
                    -0.39067524671554565,
                    -0.12259193509817123,
                    0.515160083770752,
                    0.18915344774723053,
                    0.4930802881717682,
                    0.41057491302490234,
                    -0.5572528839111328
                ],
                [
                    0.02848856709897518,
                    0.02422909624874592,
                    0.24714627861976624,
                    0.3600439131259918,
                    -0.398584246635437,
                    0.6680546402931213,
                    -0.033442217856645584,
                    -0.6814162731170654,
                    -0.35153403878211975
                ],
                [
                    0.17243337631225586,
                    0.258758544921875,
                    -0.27056142687797546,
                    0.4875204563140869,
                    -0.002336419653147459,
                    0.07707499712705612,
                    0.5489075779914856,
                    -0.9809123277664185,
                    0.11875405162572861
                ],
                [
                    0.027744024991989136,
                    -0.1846352070569992,
                    -0.4856383800506592,
                    -0.5045498013496399,
                    0.3003704845905304,
                    -0.1284419596195221,
                    0.22155599296092987,
                    0.083243228495121,
                    0.17975424230098724
                ],
                [
                    0.1847003698348999,
                    0.1438172161579132,
                    0.35981762409210205,
                    -0.05706174299120903,
                    -0.14428378641605377,
                    0.20161505043506622,
                    -0.5722513794898987,
                    -0.06797724217176437,
                    -0.43385204672813416
                ],
                [
                    -0.1733608841896057,
                    -1.4716284275054932,
                    0.43004661798477173,
                    0.2732192575931549,
                    -0.03142424300312996,
                    0.2697945535182953,
                    0.3586510717868805,
                    -0.1304570734500885,
                    -0.07556940615177155
                ],
                [
                    0.36915361881256104,
                    1.4256837368011475,
                    0.6090998649597168,
                    0.4818478226661682,
                    -0.0570172443985939,
                    -0.09164407849311829,
                    -0.49808061122894287,
                    0.3886711299419403,
                    0.6144022941589355
                ],
                [
                    -0.3443642556667328,
                    -0.32197779417037964,
                    0.05486724525690079,
                    0.2841375470161438,
                    0.36740416288375854,
                    0.35235723853111267,
                    0.04228534549474716,
                    0.6211155652999878,
                    -0.15085943043231964
                ]
            ],
            "convs.1.bias": [
                0.04841311275959015,
                -0.09065123647451401,
                0.006287714932113886,
                0.05398564413189888,
                -0.05939636752009392,
                -0.010435915552079678,
                -0.012232000939548016,
                -0.02469603717327118,
                -0.004515517503023148,
                0.04771851748228073,
                -0.0627252608537674,
                -0.08031683415174484
            ],
            "convs.1.lin.weight": [
                [
                    -0.3755434453487396,
                    0.12740452587604523,
                    -0.22519569098949432,
                    0.2583466172218323,
                    0.6208871006965637,
                    0.3804710805416107,
                    0.06473817676305771,
                    0.08699983358383179,
                    0.0018979816231876612,
                    0.18167433142662048,
                    -0.38517600297927856,
                    0.20273400843143463
                ],
                [
                    0.39240145683288574,
                    0.2849559187889099,
                    0.19771064817905426,
                    -0.35901519656181335,
                    -0.5753616094589233,
                    0.2043415904045105,
                    -0.36444196105003357,
                    0.08916473388671875,
                    0.17353060841560364,
                    -0.04478459060192108,
                    0.4120802879333496,
                    -0.5575739741325378
                ],
                [
                    -0.44060489535331726,
                    0.062210943549871445,
                    0.11803006380796432,
                    0.26459193229675293,
                    -0.3239991366863251,
                    0.0006470460793934762,
                    -0.0687473863363266,
                    0.40010786056518555,
                    0.062231678515672684,
                    0.2834610044956207,
                    -0.02042551152408123,
                    0.3158870339393616
                ],
                [
                    -0.3810705542564392,
                    -0.41060373187065125,
                    0.5066934823989868,
                    0.34017348289489746,
                    -0.42215245962142944,
                    0.220714271068573,
                    0.20943708717823029,
                    0.4104592204093933,
                    0.022025935351848602,
                    -0.10302355885505676,
                    0.09119728952646255,
                    -0.25677528977394104
                ],
                [
                    -0.20529094338417053,
                    0.35530778765678406,
                    -0.08779989928007126,
                    -0.47476351261138916,
                    -0.29805612564086914,
                    0.31672364473342896,
                    -0.20959696173667908,
                    -0.049243927001953125,
                    0.22663041949272156,
                    -0.3599548041820526,
                    0.46133357286453247,
                    -0.21159501373767853
                ],
                [
                    -0.02264348790049553,
                    0.29374781250953674,
                    0.1916881799697876,
                    0.17280496656894684,
                    0.6268337965011597,
                    -0.36313575506210327,
                    -0.2843320965766907,
                    -0.44107764959335327,
                    -0.18164193630218506,
                    0.2278299480676651,
                    -0.3708311915397644,
                    0.17985045909881592
                ],
                [
                    0.3922124207019806,
                    0.11651308834552765,
                    0.31238478422164917,
                    -0.28945448994636536,
                    -0.6355639696121216,
                    -0.2766644060611725,
                    -0.11707068979740143,
                    0.19364571571350098,
                    -0.10312929004430771,
                    -0.4969545304775238,
                    0.2796248197555542,
                    -0.8808540105819702
                ],
                [
                    -0.18309040367603302,
                    0.003467871807515621,
                    0.2091849446296692,
                    0.23924562335014343,
                    0.12475249916315079,
                    -0.4164111614227295,
                    0.4525550603866577,
                    0.4143405556678772,
                    0.497984915971756,
                    -0.46223482489585876,
                    -0.3009606599807739,
                    0.10869435966014862
                ],
                [
                    0.38927891850471497,
                    0.36294031143188477,
                    -0.24369102716445923,
                    -0.4193226397037506,
                    0.5784353613853455,
                    0.2726992666721344,
                    0.193060502409935,
                    0.11543935537338257,
                    -0.5514388084411621,
                    0.39723870158195496,
                    -0.39684057235717773,
                    -0.14137503504753113
                ],
                [
                    0.6833491921424866,
                    0.36011117696762085,
                    -0.3042563796043396,
                    0.10676603764295578,
                    -0.12367997318506241,
                    0.033848077058792114,
                    -0.2410362809896469,
                    0.33173948526382446,
                    0.0010868902318179607,
                    0.09370380640029907,
                    -0.2510639429092407,
                    -0.3232356607913971
                ],
                [
                    0.09739714115858078,
                    -0.09733030945062637,
                    -0.4410455822944641,
                    -0.281842976808548,
                    -0.15977199375629425,
                    -0.005032332614064217,
                    0.39726677536964417,
                    0.36494624614715576,
                    0.4385782778263092,
                    -0.03549899533390999,
                    0.11253856867551804,
                    0.14082641899585724
                ],
                [
                    0.16393965482711792,
                    -0.13843686878681183,
                    0.04079098626971245,
                    0.31568649411201477,
                    0.21967241168022156,
                    -0.39535197615623474,
                    -0.3417198061943054,
                    -0.3711622953414917,
                    0.23367515206336975,
                    -0.46957674622535706,
                    0.4103306233882904,
                    0.10914189368486404
                ]
            ],
            "lin_out.weight": [
                [
                    0.05067375302314758,
                    0.0399271696805954,
                    -0.1872708648443222,
                    0.26135265827178955,
                    0.26954686641693115,
                    -0.7345700860023499,
                    0.3997650742530823,
                    -0.28880199790000916,
                    -0.7066694498062134,
                    0.051490187644958496,
                    -0.10805027186870575,
                    0.19969531893730164
                ],
                [
                    -0.6367859840393066,
                    0.3390631079673767,
                    0.17728444933891296,
                    0.32671624422073364,
                    0.2193426489830017,
                    -0.40548762679100037,
                    0.4103136956691742,
                    -0.4038238525390625,
                    -0.3436325192451477,
                    -0.5086026787757874,
                    0.26065483689308167,
                    -0.684069812297821
                ],
                [
                    -0.28979581594467163,
                    0.42645642161369324,
                    0.23968912661075592,
                    -0.19666779041290283,
                    0.12741857767105103,
                    0.5821899771690369,
                    0.6129268407821655,
                    -0.37456727027893066,
                    0.13655973970890045,
                    0.8347928524017334,
                    -0.3443819582462311,
                    0.3898935914039612
                ],
                [
                    -0.6022235751152039,
                    0.4835969805717468,
                    0.08847126364707947,
                    -0.18307864665985107,
                    -0.22149431705474854,
                    -0.49512049555778503,
                    -0.10807976871728897,
                    -0.11604943871498108,
                    -0.35951194167137146,
                    0.586311399936676,
                    0.03924188390374184,
                    -0.057375095784664154
                ],
                [
                    -0.018871238455176353,
                    0.1917780190706253,
                    0.032907359302043915,
                    -0.15868942439556122,
                    -0.19631104171276093,
                    -0.04240476340055466,
                    0.1403365135192871,
                    -0.0626305639743805,
                    -0.49126800894737244,
                    -0.3352748155593872,
                    0.35226306319236755,
                    0.2856798768043518
                ],
                [
                    -0.45267534255981445,
                    0.2965252697467804,
                    0.09388288855552673,
                    0.17541080713272095,
                    0.16504478454589844,
                    -0.10935311764478683,
                    0.11187191307544708,
                    -0.021638739854097366,
                    -0.5325696468353271,
                    -0.3247750401496887,
                    0.12470360845327377,
                    0.29210588335990906
                ],
                [
                    0.10226316750049591,
                    0.5584090948104858,
                    0.05755322054028511,
                    -0.49322763085365295,
                    0.3151897192001343,
                    0.1262160688638687,
                    0.18369345366954803,
                    -0.40080711245536804,
                    -0.1593935340642929,
                    0.06046581268310547,
                    -0.26796674728393555,
                    0.08746432512998581
                ],
                [
                    0.039852727204561234,
                    0.4662719964981079,
                    -0.24775244295597076,
                    -0.29789528250694275,
                    0.21431569755077362,
                    -0.09563791006803513,
                    0.09066794812679291,
                    0.5279707312583923,
                    -0.398176372051239,
                    -0.18457236886024475,
                    -0.4562588036060333,
                    -0.20181329548358917
                ],
                [
                    -0.0726582407951355,
                    0.18077366054058075,
                    0.2673967778682709,
                    -0.5221590399742126,
                    0.7155541777610779,
                    -0.3522891104221344,
                    0.40437382459640503,
                    0.3485001027584076,
                    -0.26243457198143005,
                    -0.06808791309595108,
                    0.3690437972545624,
                    0.26195722818374634
                ],
                [
                    -0.5370066165924072,
                    -0.23971502482891083,
                    -0.4422365427017212,
                    -0.2908075153827667,
                    0.020411115139722824,
                    0.1922307014465332,
                    -0.02389257214963436,
                    -0.23427259922027588,
                    0.2799418568611145,
                    -0.025553666055202484,
                    -0.14405407011508942,
                    0.3581511080265045
                ],
                [
                    -0.28665247559547424,
                    0.5785570740699768,
                    -0.27222591638565063,
                    -0.20928946137428284,
                    0.7867059111595154,
                    0.33270227909088135,
                    -0.1975281536579132,
                    -0.46308574080467224,
                    -0.41798079013824463,
                    0.6395529508590698,
                    0.26726529002189636,
                    0.2141234129667282
                ],
                [
                    0.001474521355703473,
                    0.702266275882721,
                    -0.49380800127983093,
                    0.24785520136356354,
                    0.4971078932285309,
                    -0.19831423461437225,
                    0.5760336518287659,
                    0.5484509468078613,
                    -0.2751357853412628,
                    -0.012883943505585194,
                    0.2561193108558655,
                    0.24476324021816254
                ]
            ],
            "lin_out.bias": [
                -0.13743743300437927,
                0.250575453042984,
                0.2924654483795166,
                -0.1332319974899292,
                -0.043090444058179855,
                -0.2828095853328705,
                -0.03490860387682915,
                0.21423231065273285,
                -0.27653515338897705,
                -0.1755693554878235,
                0.015262999571859837,
                -0.22588340938091278
            ]
        }
    }
}