{
    "experiment_config": {
        "mode": "motif",
        "num_categories": 0,
        "p": 0.3,
        "num_nodes": 20,
        "motif_dim": 3,
        "chain_length_min": 2,
        "chain_length_max": 7,
        "num_train_samples": 5000,
        "num_test_samples": 1500,
        "batch_size": 4,
        "in_dim": 1,
        "hidden_dims": [
            2,
            2,
            2
        ],
        "lr": 0.01,
        "use_weighting": true,
        "importance": [
            15.0,
            10.0
        ],
        "phase1_epochs": 0,
        "phase2_epochs": 50,
        "device": "cpu",
        "model_type": "GIN",
        "loss": "BCE",
        "pooling": "mean",
        "gm_p": 1.0,
        "log_dir": "runs/motif/GIN/mean/5",
        "file_path": "motif/GIN/mean/5",
        "add_graph": false,
        "track_embeddings": false,
        "save": true
    },
    "sparcity": 0.23168435023438708,
    "summary format:": "Key: (Num of active features, Num of accurate feature, Geometry, Collapsed). Loss, s.d. Loss, Count",
    "summary": {
        "(3, 3, 3, 0)": [
            7.632488221850068e-07,
            1.0793968357823834e-06,
            3
        ],
        "(0, 0, 'Failed', 0)": [
            0.6373182776198428,
            0.001491538013969871,
            39
        ],
        "(2, 2, 2, 0)": [
            0.259623866746823,
            0.03847991368174551,
            2
        ],
        "(2, 1, 2, 0)": [
            0.21403887379707562,
            0.054162811224732044,
            3
        ],
        "(3, 3, 'Failed', 0)": [
            1.3818627981588926e-06,
            1.3914648848414989e-06,
            3
        ]
    },
    "results": [
        {
            "Num of features": 3,
            "Num of active features": 3,
            "Num of accurate feature": 3,
            "Geometry": 3,
            "Collapsed": 0,
            "Loss": 1.1895655215244547e-19,
            "Rank": 2,
            "Singular values": [
                39.42609786987305,
                22.518728256225586
            ]
        },
        {
            "Num of features": 3,
            "Num of active features": 0,
            "Num of accurate feature": 0,
            "Geometry": "Failed",
            "Collapsed": 0,
            "Loss": 0.6376976957321167,
            "Rank": 1,
            "Singular values": [
                0.189015731215477,
                2.0756754537387678e-08
            ]
        },
        {
            "Num of features": 3,
            "Num of active features": 2,
            "Num of accurate feature": 2,
            "Geometry": 2,
            "Collapsed": 0,
            "Loss": 0.22114395306507748,
            "Rank": 2,
            "Singular values": [
                2.0435924530029297,
                0.4797365665435791
            ]
        },
        {
            "Num of features": 3,
            "Num of active features": 0,
            "Num of accurate feature": 0,
            "Geometry": "Failed",
            "Collapsed": 0,
            "Loss": 0.6373932277361551,
            "Rank": 1,
            "Singular values": [
                0.14915592968463898,
                2.9443307791865436e-09
            ]
        },
        {
            "Num of features": 3,
            "Num of active features": 0,
            "Num of accurate feature": 0,
            "Geometry": "Failed",
            "Collapsed": 0,
            "Loss": 0.6363462953567505,
            "Rank": 1,
            "Singular values": [
                0.005403951741755009,
                3.6857555896219196e-10
            ]
        },
        {
            "Num of features": 3,
            "Num of active features": 0,
            "Num of accurate feature": 0,
            "Geometry": "Failed",
            "Collapsed": 0,
            "Loss": 0.6367561070124308,
            "Rank": 1,
            "Singular values": [
                0.04258064180612564,
                1.2397829984855946e-10
            ]
        },
        {
            "Num of features": 3,
            "Num of active features": 0,
            "Num of accurate feature": 0,
            "Geometry": "Failed",
            "Collapsed": 0,
            "Loss": 0.6366592421531677,
            "Rank": 1,
            "Singular values": [
                0.1141984611749649,
                9.434338643643514e-09
            ]
        },
        {
            "Num of features": 3,
            "Num of active features": 2,
            "Num of accurate feature": 1,
            "Geometry": 2,
            "Collapsed": 0,
            "Loss": 0.16548081766441464,
            "Rank": 2,
            "Singular values": [
                47.2038459777832,
                0.5868333578109741
            ]
        },
        {
            "Num of features": 3,
            "Num of active features": 0,
            "Num of accurate feature": 0,
            "Geometry": "Failed",
            "Collapsed": 0,
            "Loss": 0.6382018763224284,
            "Rank": 1,
            "Singular values": [
                0.0612797774374485,
                2.0594188576694705e-09
            ]
        },
        {
            "Num of features": 3,
            "Num of active features": 0,
            "Num of accurate feature": 0,
            "Geometry": "Failed",
            "Collapsed": 0,
            "Loss": 0.6359046842257182,
            "Rank": 1,
            "Singular values": [
                0.03940585255622864,
                1.3732325276905044e-09
            ]
        },
        {
            "Num of features": 3,
            "Num of active features": 0,
            "Num of accurate feature": 0,
            "Geometry": "Failed",
            "Collapsed": 0,
            "Loss": 0.6372523450851441,
            "Rank": 1,
            "Singular values": [
                0.0013409629464149475,
                1.3894809781922479e-11
            ]
        },
        {
            "Num of features": 3,
            "Num of active features": 0,
            "Num of accurate feature": 0,
            "Geometry": "Failed",
            "Collapsed": 0,
            "Loss": 0.6365529241561889,
            "Rank": 1,
            "Singular values": [
                0.0311826653778553,
                6.795060070174941e-10
            ]
        },
        {
            "Num of features": 3,
            "Num of active features": 0,
            "Num of accurate feature": 0,
            "Geometry": "Failed",
            "Collapsed": 0,
            "Loss": 0.6371677385965983,
            "Rank": 1,
            "Singular values": [
                0.034035827964544296,
                1.3388700148553312e-09
            ]
        },
        {
            "Num of features": 3,
            "Num of active features": 0,
            "Num of accurate feature": 0,
            "Geometry": "Failed",
            "Collapsed": 0,
            "Loss": 0.6367171850204468,
            "Rank": 1,
            "Singular values": [
                0.004066134337335825,
                2.5608000095433958e-11
            ]
        },
        {
            "Num of features": 3,
            "Num of active features": 0,
            "Num of accurate feature": 0,
            "Geometry": "Failed",
            "Collapsed": 0,
            "Loss": 0.6365757727622986,
            "Rank": 1,
            "Singular values": [
                0.02585904859006405,
                3.71141117838647e-10
            ]
        },
        {
            "Num of features": 3,
            "Num of active features": 0,
            "Num of accurate feature": 0,
            "Geometry": "Failed",
            "Collapsed": 0,
            "Loss": 0.636904243628184,
            "Rank": 1,
            "Singular values": [
                0.01587551459670067,
                2.7872540386830735e-10
            ]
        },
        {
            "Num of features": 3,
            "Num of active features": 0,
            "Num of accurate feature": 0,
            "Geometry": "Failed",
            "Collapsed": 0,
            "Loss": 0.6368041068712871,
            "Rank": 1,
            "Singular values": [
                0.0011383636156097054,
                4.199173994634542e-11
            ]
        },
        {
            "Num of features": 3,
            "Num of active features": 0,
            "Num of accurate feature": 0,
            "Geometry": "Failed",
            "Collapsed": 0,
            "Loss": 0.637304854075114,
            "Rank": 1,
            "Singular values": [
                0.15099120140075684,
                1.5234974393152356e-10
            ]
        },
        {
            "Num of features": 3,
            "Num of active features": 0,
            "Num of accurate feature": 0,
            "Geometry": "Failed",
            "Collapsed": 0,
            "Loss": 0.6364672301610311,
            "Rank": 1,
            "Singular values": [
                0.056426506489515305,
                2.899489259799992e-10
            ]
        },
        {
            "Num of features": 3,
            "Num of active features": 0,
            "Num of accurate feature": 0,
            "Geometry": "Failed",
            "Collapsed": 0,
            "Loss": 0.6369962417284648,
            "Rank": 1,
            "Singular values": [
                0.0044760387390851974,
                9.195803146733184e-11
            ]
        },
        {
            "Num of features": 3,
            "Num of active features": 3,
            "Num of accurate feature": 3,
            "Geometry": 3,
            "Collapsed": 0,
            "Loss": 2.289746466531058e-06,
            "Rank": 2,
            "Singular values": [
                6.162869453430176,
                1.324422001838684
            ]
        },
        {
            "Num of features": 3,
            "Num of active features": 0,
            "Num of accurate feature": 0,
            "Geometry": "Failed",
            "Collapsed": 0,
            "Loss": 0.6364568405151367,
            "Rank": 1,
            "Singular values": [
                0.025180546566843987,
                1.1073338912481745e-09
            ]
        },
        {
            "Num of features": 3,
            "Num of active features": 0,
            "Num of accurate feature": 0,
            "Geometry": "Failed",
            "Collapsed": 0,
            "Loss": 0.6363922384579976,
            "Rank": 1,
            "Singular values": [
                0.06058363988995552,
                1.0493861335447718e-09
            ]
        },
        {
            "Num of features": 3,
            "Num of active features": 0,
            "Num of accurate feature": 0,
            "Geometry": "Failed",
            "Collapsed": 0,
            "Loss": 0.6361517950693766,
            "Rank": 1,
            "Singular values": [
                0.0013351939851418138,
                6.401678232653696e-12
            ]
        },
        {
            "Num of features": 3,
            "Num of active features": 0,
            "Num of accurate feature": 0,
            "Geometry": "Failed",
            "Collapsed": 0,
            "Loss": 0.6361150886217753,
            "Rank": 1,
            "Singular values": [
                0.0009685200056992471,
                1.9312655641368082e-11
            ]
        },
        {
            "Num of features": 3,
            "Num of active features": 0,
            "Num of accurate feature": 0,
            "Geometry": "Failed",
            "Collapsed": 0,
            "Loss": 0.6397031440734863,
            "Rank": 1,
            "Singular values": [
                0.03820030763745308,
                3.7453994766734056e-11
            ]
        },
        {
            "Num of features": 3,
            "Num of active features": 2,
            "Num of accurate feature": 2,
            "Geometry": 2,
            "Collapsed": 0,
            "Loss": 0.2981037804285685,
            "Rank": 2,
            "Singular values": [
                1.9850611686706543,
                0.9147076606750488
            ]
        },
        {
            "Num of features": 3,
            "Num of active features": 0,
            "Num of accurate feature": 0,
            "Geometry": "Failed",
            "Collapsed": 0,
            "Loss": 0.6366946994463603,
            "Rank": 1,
            "Singular values": [
                0.011929337866604328,
                3.10049416696323e-11
            ]
        },
        {
            "Num of features": 3,
            "Num of active features": 0,
            "Num of accurate feature": 0,
            "Geometry": "Failed",
            "Collapsed": 0,
            "Loss": 0.6400398596127828,
            "Rank": 1,
            "Singular values": [
                0.003593875328078866,
                2.024672929312743e-10
            ]
        },
        {
            "Num of features": 3,
            "Num of active features": 0,
            "Num of accurate feature": 0,
            "Geometry": "Failed",
            "Collapsed": 0,
            "Loss": 0.638882530371348,
            "Rank": 1,
            "Singular values": [
                0.07037808746099472,
                3.842508089491048e-09
            ]
        },
        {
            "Num of features": 3,
            "Num of active features": 0,
            "Num of accurate feature": 0,
            "Geometry": "Failed",
            "Collapsed": 0,
            "Loss": 0.6364830123583476,
            "Rank": 1,
            "Singular values": [
                0.02693329006433487,
                9.953760038428072e-10
            ]
        },
        {
            "Num of features": 3,
            "Num of active features": 0,
            "Num of accurate feature": 0,
            "Geometry": "Failed",
            "Collapsed": 0,
            "Loss": 0.6365477353731791,
            "Rank": 1,
            "Singular values": [
                0.24062304198741913,
                1.1005979239087083e-08
            ]
        },
        {
            "Num of features": 3,
            "Num of active features": 0,
            "Num of accurate feature": 0,
            "Geometry": "Failed",
            "Collapsed": 0,
            "Loss": 0.6367218804359436,
            "Rank": 1,
            "Singular values": [
                0.000644880230538547,
                1.0244765973055348e-11
            ]
        },
        {
            "Num of features": 3,
            "Num of active features": 0,
            "Num of accurate feature": 0,
            "Geometry": "Failed",
            "Collapsed": 0,
            "Loss": 0.6365629849433899,
            "Rank": 1,
            "Singular values": [
                0.13392890989780426,
                3.6921821155999623e-10
            ]
        },
        {
            "Num of features": 3,
            "Num of active features": 0,
            "Num of accurate feature": 0,
            "Geometry": "Failed",
            "Collapsed": 0,
            "Loss": 0.6363893618583679,
            "Rank": 1,
            "Singular values": [
                0.11952929943799973,
                1.289686246686017e-09
            ]
        },
        {
            "Num of features": 3,
            "Num of active features": 2,
            "Num of accurate feature": 1,
            "Geometry": 2,
            "Collapsed": 0,
            "Loss": 0.28962093849976855,
            "Rank": 2,
            "Singular values": [
                1.7286720275878906,
                0.15858317911624908
            ]
        },
        {
            "Num of features": 3,
            "Num of active features": 2,
            "Num of accurate feature": 1,
            "Geometry": 2,
            "Collapsed": 0,
            "Loss": 0.18701486522704364,
            "Rank": 2,
            "Singular values": [
                34.90799331665039,
                1.753108024597168
            ]
        },
        {
            "Num of features": 3,
            "Num of active features": 0,
            "Num of accurate feature": 0,
            "Geometry": "Failed",
            "Collapsed": 0,
            "Loss": 0.6365748550097148,
            "Rank": 1,
            "Singular values": [
                0.0011678742012009025,
                3.857857176076118e-12
            ]
        },
        {
            "Num of features": 3,
            "Num of active features": 3,
            "Num of accurate feature": 3,
            "Geometry": 3,
            "Collapsed": 0,
            "Loss": 2.3843494000732243e-17,
            "Rank": 2,
            "Singular values": [
                26.670434951782227,
                12.564536094665527
            ]
        },
        {
            "Num of features": 3,
            "Num of active features": 0,
            "Num of accurate feature": 0,
            "Geometry": "Failed",
            "Collapsed": 0,
            "Loss": 0.6367284073829651,
            "Rank": 1,
            "Singular values": [
                0.0016000508330762386,
                9.246611115676373e-11
            ]
        },
        {
            "Num of features": 3,
            "Num of active features": 0,
            "Num of accurate feature": 0,
            "Geometry": "Failed",
            "Collapsed": 0,
            "Loss": 0.6429616441726684,
            "Rank": 1,
            "Singular values": [
                0.2817049026489258,
                1.5364909344839361e-09
            ]
        },
        {
            "Num of features": 3,
            "Num of active features": 0,
            "Num of accurate feature": 0,
            "Geometry": "Failed",
            "Collapsed": 0,
            "Loss": 0.6374701352119446,
            "Rank": 1,
            "Singular values": [
                0.007568157743662596,
                3.211548527115582e-10
            ]
        },
        {
            "Num of features": 3,
            "Num of active features": 3,
            "Num of accurate feature": 3,
            "Geometry": "Failed",
            "Collapsed": 0,
            "Loss": 1.1564601224618867e-09,
            "Rank": 2,
            "Singular values": [
                10.895102500915527,
                3.7512543201446533
            ]
        },
        {
            "Num of features": 3,
            "Num of active features": 0,
            "Num of accurate feature": 0,
            "Geometry": "Failed",
            "Collapsed": 0,
            "Loss": 0.6374633735020956,
            "Rank": 1,
            "Singular values": [
                0.03495480865240097,
                2.1410814787792276e-10
            ]
        },
        {
            "Num of features": 3,
            "Num of active features": 0,
            "Num of accurate feature": 0,
            "Geometry": "Failed",
            "Collapsed": 0,
            "Loss": 0.6420500909487407,
            "Rank": 1,
            "Singular values": [
                4.002065181732178,
                2.2647279251941654e-07
            ]
        },
        {
            "Num of features": 3,
            "Num of active features": 0,
            "Num of accurate feature": 0,
            "Geometry": "Failed",
            "Collapsed": 0,
            "Loss": 0.6371066328684489,
            "Rank": 1,
            "Singular values": [
                0.02164975367486477,
                9.82170039742769e-11
            ]
        },
        {
            "Num of features": 3,
            "Num of active features": 0,
            "Num of accurate feature": 0,
            "Geometry": "Failed",
            "Collapsed": 0,
            "Loss": 0.6365529311498006,
            "Rank": 1,
            "Singular values": [
                0.07418841123580933,
                1.204086719219788e-09
            ]
        },
        {
            "Num of features": 3,
            "Num of active features": 3,
            "Num of accurate feature": 3,
            "Geometry": "Failed",
            "Collapsed": 0,
            "Loss": 3.286505592719536e-06,
            "Rank": 2,
            "Singular values": [
                66.84620666503906,
                3.3876068592071533
            ]
        },
        {
            "Num of features": 3,
            "Num of active features": 3,
            "Num of accurate feature": 3,
            "Geometry": "Failed",
            "Collapsed": 0,
            "Loss": 8.579263416346796e-07,
            "Rank": 2,
            "Singular values": [
                32.079994201660156,
                2.546069860458374
            ]
        },
        {
            "Num of features": 3,
            "Num of active features": 0,
            "Num of accurate feature": 0,
            "Geometry": "Failed",
            "Collapsed": 0,
            "Loss": 0.6376618151664734,
            "Rank": 1,
            "Singular values": [
                0.1830005943775177,
                7.644644028914627e-09
            ]
        }
    ],
    "average embeddings summary": {
        "(3, 3, 3, 0)": {
            "(0, 1, 0)": [
                23.565153121948242,
                18.383106231689453
            ],
            "(1, 0, 0)": [
                0.10268140584230423,
                -6.6165690422058105
            ],
            "(0, 0, 1)": [
                -31.528583526611328,
                11.41989803314209
            ]
        },
        "(0, 0, 'Failed', 0)": {
            "(1, 0, 0)": [
                -0.09068331867456436,
                -0.060708481818437576
            ],
            "(0, 0, 1)": [
                -0.09068328887224197,
                -0.06070849671959877
            ],
            "(0, 1, 0)": [
                -0.09068331122398376,
                -0.06070848926901817
            ]
        },
        "(2, 2, 2, 0)": {
            "(0, 1, 0)": [
                -0.061399128288030624,
                -0.3739859461784363
            ],
            "(1, 0, 0)": [
                1.141156554222107,
                0.372721403837204
            ],
            "(0, 0, 1)": [
                -1.2605496644973755,
                -1.1102417707443237
            ]
        },
        "(2, 1, 2, 0)": {
            "(0, 1, 0)": [
                -0.2675762176513672,
                -0.4707472026348114
            ],
            "(0, 0, 1)": [
                -46.36472702026367,
                -8.849918365478516
            ],
            "(1, 0, 0)": [
                0.33947402238845825,
                -0.36040249466896057
            ]
        },
        "(3, 3, 'Failed', 0)": {
            "(0, 0, 1)": [
                -4.284965991973877,
                -8.629963874816895
            ],
            "(0, 1, 0)": [
                -0.5628936886787415,
                4.794332981109619
            ],
            "(1, 0, 0)": [
                3.7672975063323975,
                1.5629969835281372
            ]
        }
    },
    "model summary": {
        "(3, 3, 3, 0)": {
            "convs.0.eps": [
                0.0
            ],
            "convs.0.nn.0.weight": [
                [
                    -0.8279938697814941
                ],
                [
                    -0.08290064334869385
                ]
            ],
            "convs.0.nn.0.bias": [
                -0.4528679847717285,
                -0.4563177824020386
            ],
            "convs.0.nn.2.weight": [
                [
                    0.44080764055252075,
                    -0.6436614990234375
                ],
                [
                    0.05617576465010643,
                    -0.5098578929901123
                ]
            ],
            "convs.0.nn.2.bias": [
                -0.2644455134868622,
                0.9543272256851196
            ],
            "convs.1.eps": [
                -1.7710736989974976
            ],
            "convs.1.nn.0.weight": [
                [
                    0.23809218406677246,
                    -0.40365859866142273
                ],
                [
                    -0.21760712563991547,
                    0.886461615562439
                ]
            ],
            "convs.1.nn.0.bias": [
                2.015289068222046,
                -0.5519774556159973
            ],
            "convs.1.nn.2.weight": [
                [
                    -4.5397257804870605,
                    0.667909562587738
                ],
                [
                    -2.279599666595459,
                    1.0285500288009644
                ]
            ],
            "convs.1.nn.2.bias": [
                -0.2719862163066864,
                -0.4860377013683319
            ],
            "convs.2.eps": [
                1.6987303495407104
            ],
            "convs.2.nn.0.weight": [
                [
                    -5.22430419921875,
                    3.457181453704834
                ],
                [
                    2.1003916263580322,
                    1.027857780456543
                ]
            ],
            "convs.2.nn.0.bias": [
                -6.817752364440821e-06,
                -1.1706292629241943
            ],
            "convs.2.nn.2.weight": [
                [
                    2.9884519577026367,
                    -2.230950117111206
                ],
                [
                    2.284860849380493,
                    1.265360951423645
                ]
            ],
            "convs.2.nn.2.bias": [
                0.10268142074346542,
                -6.616568565368652
            ],
            "lin_out.weight": [
                [
                    1.6689385175704956,
                    -6.2257232666015625
                ],
                [
                    2.2147576808929443,
                    3.682635545730591
                ],
                [
                    -3.7126734256744385,
                    3.370309591293335
                ]
            ],
            "lin_out.bias": [
                0.010002466849982738,
                -3.9567883014678955,
                -5.486141204833984
            ]
        },
        "(0, 0, 'Failed', 0)": {
            "convs.0.eps": [
                0.0
            ],
            "convs.0.nn.0.weight": [
                [
                    -0.584078311920166
                ],
                [
                    -0.6929624080657959
                ]
            ],
            "convs.0.nn.0.bias": [
                -0.340509295463562,
                0.5615183115005493
            ],
            "convs.0.nn.2.weight": [
                [
                    -0.20591601729393005,
                    0.31065911054611206
                ],
                [
                    -0.16216573119163513,
                    -0.20039258897304535
                ]
            ],
            "convs.0.nn.2.bias": [
                -0.5448580384254456,
                0.4415106773376465
            ],
            "convs.1.eps": [
                -0.09009816497564316
            ],
            "convs.1.nn.0.weight": [
                [
                    0.2586807310581207,
                    0.5526571273803711
                ],
                [
                    0.21323421597480774,
                    -0.12659834325313568
                ]
            ],
            "convs.1.nn.0.bias": [
                -0.39322179555892944,
                -0.4184522032737732
            ],
            "convs.1.nn.2.weight": [
                [
                    0.09479204565286636,
                    0.034935690462589264
                ],
                [
                    0.10580785572528839,
                    -0.3061144948005676
                ]
            ],
            "convs.1.nn.2.bias": [
                0.13883067667484283,
                0.5121155977249146
            ],
            "convs.2.eps": [
                -0.08942786604166031
            ],
            "convs.2.nn.0.weight": [
                [
                    0.49444082379341125,
                    -0.43769320845603943
                ],
                [
                    -0.40311479568481445,
                    0.18464381992816925
                ]
            ],
            "convs.2.nn.0.bias": [
                -0.3631468117237091,
                -0.2068590521812439
            ],
            "convs.2.nn.2.weight": [
                [
                    0.13737472891807556,
                    -0.22170805931091309
                ],
                [
                    0.5652936100959778,
                    -0.5635125637054443
                ]
            ],
            "convs.2.nn.2.bias": [
                -0.09068328887224197,
                -0.06070848926901817
            ],
            "lin_out.weight": [
                [
                    -0.10656578093767166,
                    -0.08965757489204407
                ],
                [
                    0.2294895499944687,
                    0.15607723593711853
                ],
                [
                    -0.1177869439125061,
                    -0.08341364562511444
                ]
            ],
            "lin_out.bias": [
                -0.695320725440979,
                -0.7863451838493347,
                -0.6010344624519348
            ]
        },
        "(2, 2, 2, 0)": {
            "convs.0.eps": [
                0.09549276530742645
            ],
            "convs.0.nn.0.weight": [
                [
                    -0.8405935764312744
                ],
                [
                    0.5230210423469543
                ]
            ],
            "convs.0.nn.0.bias": [
                -0.0836329460144043,
                0.5303017497062683
            ],
            "convs.0.nn.2.weight": [
                [
                    -0.2879650592803955,
                    -0.38076525926589966
                ],
                [
                    0.6419692635536194,
                    -0.1103585734963417
                ]
            ],
            "convs.0.nn.2.bias": [
                0.48287034034729004,
                -0.5277591943740845
            ],
            "convs.1.eps": [
                -0.07377716898918152
            ],
            "convs.1.nn.0.weight": [
                [
                    0.5719180107116699,
                    -0.37827226519584656
                ],
                [
                    -0.16407126188278198,
                    0.5245187878608704
                ]
            ],
            "convs.1.nn.0.bias": [
                1.1415414810180664,
                0.8617326617240906
            ],
            "convs.1.nn.2.weight": [
                [
                    0.7648060321807861,
                    1.0986418724060059
                ],
                [
                    -0.8208787441253662,
                    0.3788797855377197
                ]
            ],
            "convs.1.nn.2.bias": [
                0.9102148413658142,
                0.31597980856895447
            ],
            "convs.2.eps": [
                -3.8129711151123047
            ],
            "convs.2.nn.0.weight": [
                [
                    1.6499345302581787,
                    0.14477688074111938
                ],
                [
                    -1.9983553886413574,
                    0.18084681034088135
                ]
            ],
            "convs.2.nn.0.bias": [
                -0.49501898884773254,
                0.6294031143188477
            ],
            "convs.2.nn.2.weight": [
                [
                    -1.3269760608673096,
                    2.3110737800598145
                ],
                [
                    -0.8201426863670349,
                    1.038313627243042
                ]
            ],
            "convs.2.nn.2.bias": [
                0.3567126393318176,
                0.2854635715484619
            ],
            "lin_out.weight": [
                [
                    7.080246448516846,
                    33.80008316040039
                ],
                [
                    0.041876185685396194,
                    0.172592431306839
                ],
                [
                    -25.91412353515625,
                    -1.7173486948013306
                ]
            ],
            "lin_out.bias": [
                -7.508690357208252,
                -0.788823664188385,
                -5.41765832901001
            ]
        },
        "(2, 1, 2, 0)": {
            "convs.0.eps": [
                0.0
            ],
            "convs.0.nn.0.weight": [
                [
                    0.5090610980987549
                ],
                [
                    -0.36799705028533936
                ]
            ],
            "convs.0.nn.0.bias": [
                0.4199317693710327,
                0.7216910123825073
            ],
            "convs.0.nn.2.weight": [
                [
                    0.4303731918334961,
                    0.6941945552825928
                ],
                [
                    -0.21227790415287018,
                    -0.18118003010749817
                ]
            ],
            "convs.0.nn.2.bias": [
                0.2616358995437622,
                -0.4410366714000702
            ],
            "convs.1.eps": [
                0.0
            ],
            "convs.1.nn.0.weight": [
                [
                    -0.5589858293533325,
                    0.47182655334472656
                ],
                [
                    -0.49590444564819336,
                    0.22931906580924988
                ]
            ],
            "convs.1.nn.0.bias": [
                -0.5302897691726685,
                -0.6208341121673584
            ],
            "convs.1.nn.2.weight": [
                [
                    -0.6552425622940063,
                    -0.3867846429347992
                ],
                [
                    0.390756756067276,
                    0.4139751195907593
                ]
            ],
            "convs.1.nn.2.bias": [
                4.369721412658691,
                -0.45401132106781006
            ],
            "convs.2.eps": [
                -5.8264312744140625
            ],
            "convs.2.nn.0.weight": [
                [
                    4.552942752838135,
                    0.019692102447152138
                ],
                [
                    0.10951736569404602,
                    0.355606347322464
                ]
            ],
            "convs.2.nn.0.bias": [
                -3.18440842628479,
                -0.8331560492515564
            ],
            "convs.2.nn.2.weight": [
                [
                    -11.439976692199707,
                    -0.0054964907467365265
                ],
                [
                    -2.0794687271118164,
                    0.10576566308736801
                ]
            ],
            "convs.2.nn.2.bias": [
                0.33947405219078064,
                -0.360402375459671
            ],
            "lin_out.weight": [
                [
                    43.5809211730957,
                    11.240446090698242
                ],
                [
                    0.08278300613164902,
                    0.121254563331604
                ],
                [
                    -1.9382810592651367,
                    5.183707237243652
                ]
            ],
            "lin_out.bias": [
                -1.7888752222061157,
                0.0406639501452446,
                -16.231552124023438
            ]
        },
        "(3, 3, 'Failed', 0)": {
            "convs.0.eps": [
                -0.9164578914642334
            ],
            "convs.0.nn.0.weight": [
                [
                    -0.3099018335342407
                ],
                [
                    0.572836697101593
                ]
            ],
            "convs.0.nn.0.bias": [
                0.35666751861572266,
                -0.6860462427139282
            ],
            "convs.0.nn.2.weight": [
                [
                    0.13672909140586853,
                    -0.6451526284217834
                ],
                [
                    0.0780218243598938,
                    0.7394299507141113
                ]
            ],
            "convs.0.nn.2.bias": [
                0.13650880753993988,
                -1.0319393873214722
            ],
            "convs.1.eps": [
                -0.09483777731657028
            ],
            "convs.1.nn.0.weight": [
                [
                    -0.8511393666267395,
                    -0.6709429621696472
                ],
                [
                    0.0777762159705162,
                    0.8596527576446533
                ]
            ],
            "convs.1.nn.0.bias": [
                -0.06825213879346848,
                -0.9699147343635559
            ],
            "convs.1.nn.2.weight": [
                [
                    0.11990900337696075,
                    2.4044742584228516
                ],
                [
                    0.2962515950202942,
                    -0.3985842168331146
                ]
            ],
            "convs.1.nn.2.bias": [
                -0.3255513608455658,
                1.6774511337280273
            ],
            "convs.2.eps": [
                -2.8205716609954834
            ],
            "convs.2.nn.0.weight": [
                [
                    0.7317894101142883,
                    -1.4354645013809204
                ],
                [
                    -1.0951695442199707,
                    1.43992018699646
                ]
            ],
            "convs.2.nn.0.bias": [
                -0.6224411725997925,
                1.45992910861969
            ],
            "convs.2.nn.2.weight": [
                [
                    -0.6797705888748169,
                    1.9452873468399048
                ],
                [
                    -2.4971957206726074,
                    -1.4720771312713623
                ]
            ],
            "convs.2.nn.2.bias": [
                -4.614391326904297,
                7.905758380889893
            ],
            "lin_out.weight": [
                [
                    13.9009428024292,
                    -3.61381196975708
                ],
                [
                    -8.568705558776855,
                    7.157252311706543
                ],
                [
                    -2.2492918968200684,
                    -7.214592933654785
                ]
            ],
            "lin_out.bias": [
                -21.37428092956543,
                0.41453972458839417,
                -1.446083426475525
            ]
        }
    }
}